markov/__init__.py
prog_lang_detector/__init__.py
prog_lang_detector/classify.py
prog_lang_detector/generate_models.py
prog_lang_detector/markov/__init__.py
prog_lang_detector/models/c.json
prog_lang_detector/models/cpp.json
prog_lang_detector/models/java.json
prog_lang_detector/models/python.json
prog_lang_detector/models/tinySelf.json
prog_lang_detector-0.2.dist-info/LICENSE
prog_lang_detector-0.2.dist-info/METADATA
prog_lang_detector-0.2.dist-info/WHEEL
prog_lang_detector-0.2.dist-info/entry_points.txt
prog_lang_detector-0.2.dist-info/top_level.txt
prog_lang_detector-0.2.dist-info/RECORD
